[
    {
        "name": "batch_size",
        "default": 25,
        "type": "int",
        "values": [],
        "tooltip": "input batch size",
        "changeable": false
    },
    {
        "name": "loadSize",
        "default": 256,
        "type": "int",
        "values": [],
        "tooltip": "scale images to this size",
        "changeable": false
    },
    {
        "name": "fineSize",
        "default": 256,
        "type": "int",
        "values": [],
        "tooltip": "then crop to this size",
        "changeable": false
    },
    {
        "name": "input_nc",
        "default": 1,
        "type": "int",
        "values": [],
        "tooltip": "# of input image channels",
        "changeable": false
    },
    {
        "name": "output_nc",
        "default": 2,
        "type": "int",
        "values": [],
        "tooltip": "# of output image channels",
        "changeable": false
    },
    {
        "name": "ngf",
        "default": 64,
        "type": "int",
        "values": [],
        "tooltip": "# of gen filters in first conv layer",
        "changeable": false
    },
    {
        "name": "ndf",
        "default": 64,
        "type": "int",
        "values": [],
        "tooltip": "# of discrim filters in first conv layer",
        "changeable": false
    },
    {
        "name": "which_model_netD",
        "default": "basic",
        "type": "string",
        "values": [],
        "tooltip": "selects model to use for netD",
        "changeable": false
    },
    {
        "name": "which_model_netG",
        "default": "siggraph",
        "type": "string",
        "values": [],
        "tooltip": "selects model to use for netG",
        "changeable": false
    },
    {
        "name": "n_layers_D",
        "default": 3,
        "type": "int",
        "values": [],
        "tooltip": "only used if which_model_netD==n_layers",
        "changeable": false
    },
    {
        "name": "gpu_ids",
        "default": [0],
        "type": "array",
        "values": [[-1], [0]],
        "tooltip": "gpu ids: e.g. 0  0,1,2, 0,2. use -1 for CPU",
        "changeable": false
    },
    {
        "name": "dataset_mode",
        "default": "aligned",
        "type": "string",
        "values": ["unaligned", "aligned", "single"],
        "tooltip": "chooses how datasets are loaded. [unaligned | aligned | single]",
        "changeable": false
    },
    {
        "name": "which_direction",
        "default": "AtoB",
        "type": "string",
        "values": ["AtoB", "BtoA"],
        "tooltip": "AtoB or BtoA",
        "changeable": false
    },
    {
        "name": "nThreads",
        "default": 4,
        "type": "int",
        "values": [],
        "tooltip": "# threads for loading data",
        "changeable": false
    },
    {
        "name": "checkpoints_dir",
        "default": "./checkpoints",
        "type": "string",
        "values": [],
        "tooltip": "models are saved here",
        "changeable": false
    },
    {
        "name": "norm",
        "default": "batch",
        "type": "string",
        "values": [],
        "tooltip": "instance normalization or batch normalization",
        "changeable": false
    },
    {
        "name": "serial_batches",
        "default": true,
        "type": "bool",
        "values": [true, false],
        "tooltip": "if true, takes images in order to make batches, otherwise takes them randomly",
        "changeable": false
    },
    {
        "name": "display_winsize",
        "default": 256,
        "type": "int",
        "values": [],
        "tooltip": "display window size",
        "changeable": false
    },
    {
        "name": "display_id",
        "default": 1,
        "type": "int",
        "values": [],
        "tooltip": "window id of the web display",
        "changeable": false
    },
    {
        "name": "display_server",
        "default": "http://localhost",
        "type": "string",
        "values": [],
        "tooltip": "visdom server of the web display",
        "changeable": false
    },
    {
        "name": "display_port",
        "default": 8097,
        "type": "int",
        "values": [],
        "tooltip": "visdom port of the web display",
        "changeable": false
    },
    {
        "name": "no_dropout",
        "default": true,
        "type": "bool",
        "values": [true, false],
        "tooltip": "no dropout for the generator",
        "changeable": false
    },
    {
        "name": "max_dataset_size",
        "default": 99999999,
        "type": "int",
        "values": [],
        "tooltip": "Maximum number of samples allowed per dataset. If the dataset directory contains more than max_dataset_size, only a subset is loaded.",
        "changeable": false
    },
    {
        "name": "resize_or_crop",
        "default": "resize_and_crop",
        "type": "string",
        "values": ["resize_and_crop", "crop", "scale_width", "scale_width_and_crop"],
        "tooltip": "scaling and cropping of images at load time [resize_and_crop|crop|scale_width|scale_width_and_crop]",
        "changeable": false
    },
    {
        "name": "no_flip",
        "default": true,
        "type": "bool",
        "values": [true, false],
        "tooltip": "if specified, do not flip the images for data augmentation",
        "changeable": false
    },
    {
        "name": "init_type",
        "default": "normal",
        "type": "string",
        "values": ["normal", "xavier", "kaiming", "orthogonal"],
        "tooltip": "network initialization [normal|xavier|kaiming|orthogonal]",
        "changeable": false
    },
    {
        "name": "verbose",
        "default": true,
        "type": "bool",
        "values": [true, false],
        "tooltip": "if specified, print more debugging information",
        "changeable": false
    },
    {
        "name": "suffix",
        "default": "",
        "type": "string",
        "values": [],
        "tooltip": "customized suffix: opt.name = opt.name + suffix",
        "changeable": false
    },
    {
        "name": "ab_norm",
        "default": 110.0,
        "type": "float",
        "values": [],
        "tooltip": "colorization normalization factor",
        "changeable": false
    },
    {
        "name": "ab_max",
        "default": 110.0,
        "type": "float",
        "values": [],
        "tooltip": "maximimum ab value",
        "changeable": false
    },
    {
        "name": "ab_quant",
        "default": 10.0,
        "type": "float",
        "values": [],
        "tooltip": "quantization factor",
        "changeable": false
    },
    {
        "name": "l_norm",
        "default": 100.0,
        "type": "float",
        "values": [],
        "tooltip": "colorization normalization factor",
        "changeable": false
    },
    {
        "name": "l_cent",
        "default": 50.0,
        "type": "float",
        "values": [],
        "tooltip": "colorization centering factor",
        "changeable": false
    },
    {
        "name": "mask_cent",
        "default": 0.5,
        "type": "float",
        "values": [],
        "tooltip": "mask centering factor",
        "changeable": false
    },
    {
        "name": "sample_p",
        "default": 1.0,
        "type": "float",
        "values": [],
        "tooltip": "sampling geometric distribution, 1.0 means no hints",
        "changeable": false
    },
    {
        "name": "sample_Ps",
        "default": 1,
        "type": "int",
        "values": [1, 2, 3, 4, 5, 6, 7, 8, 9],
        "tooltip": "sampling geometric distribution, 1.0 means no hints",
        "changeable": false
    },
    {
        "name": "results_dir",
        "default": "./results/",
        "type": "string",
        "values": [],
        "tooltip": "saves results here.",
        "changeable": false
    },
    {
        "name": "classification",
        "default": true,
        "type": "bool",
        "values": [true, false],
        "tooltip": "backprop trunk using classification, otherwise use regression",
        "changeable": false
    },
    {
        "name": "phase",
        "default": "val",
        "type": "string",
        "values": ["train_small", "train", "val", "test"],
        "tooltip": "train_small, train, val, test, etc",
        "changeable": false
    },
    {
        "name": "which_epoch",
        "default": "latest",
        "type": "string",
        "values": [],
        "tooltip": "which epoch to load? set to latest to use latest cached model",
        "changeable": false
    },
    {
        "name": "how_many",
        "default": 200,
        "type": "int",
        "values": [],
        "tooltip": "how many test images to run",
        "changeable": false
    },
    {
        "name": "aspect_ratio",
        "default": 1.0,
        "type": "float",
        "values": [],
        "tooltip": "aspect ratio of result images",
        "changeable": false
    },
    {
        "name": "load_model",
        "default": true,
        "type": "bool",
        "values": [true, false],
        "tooltip": "load the latest model",
        "changeable": false
    },
    {
        "name": "half",
        "default": true,
        "type": "bool",
        "values": [true, false],
        "tooltip": "half precision model",
        "changeable": false
    },
    {
        "name": "test_img_dir",
        "default": "example",
        "type": "string",
        "values": [],
        "tooltip": "testing images folder",
        "changeable": false
    },
    {
        "name": "results_img_dir",
        "default": "results",
        "type": "string",
        "values": [],
        "tooltip": "save the results image folder",
        "changeable": false
    },
    {
        "name": "name",
        "default": "test_fusion",
        "type": "string",
        "values": [],
        "tooltip": "name of the experiment. It decides where to store samples and models",
        "changeable": false
    },
    {
        "name": "model",
        "default": "fusion",
        "type": "string",
        "values": ["cycle_gan", "pix2pix", "test"],
        "tooltip": "chooses which model to use. cycle_gan, pix2pix, test",
        "changeable": true
    },
    {
        "name": "display_freq",
        "default": 2000,
        "type": "int",
        "values": [],
        "tooltip": "frequency of showing training results on screen",
        "changeable": false
    },
    {
        "name": "display_ncols",
        "default": 5,
        "type": "int",
        "values": [],
        "tooltip": "if positive, display all images in a single visdom web panel with certain number of images per row.",
        "changeable": false
    },
    {
        "name": "update_html_freq",
        "default": 10000,
        "type": "int",
        "values": [],
        "tooltip": "frequency of saving training results to html",
        "changeable": false
    },
    {
        "name": "print_freq",
        "default": 2000,
        "type": "int",
        "values": [],
        "tooltip": "frequency of showing training results on console",
        "changeable": false
    },
    {
        "name": "save_latest_freq",
        "default": 5000,
        "type": "int",
        "values": [],
        "tooltip": "frequency of saving the latest results",
        "changeable": false
    },
    {
        "name": "save_epoch_freq",
        "default": 1,
        "type": "int",
        "values": [],
        "tooltip": "frequency of saving checkpoints at the end of epochs",
        "changeable": false
    },
    {
        "name": "epoch_count",
        "default": 0,
        "type": "int",
        "values": [],
        "tooltip": "the starting epoch count, we save the model by <epoch_count>, <epoch_count>+<save_latest_freq>, ...",
        "changeable": false
    },
    {
        "name": "niter",
        "default": 100,
        "type": "int",
        "values": [],
        "tooltip": "# of iter at starting learning rate",
        "changeable": false
    },
    {
        "name": "niter_decay",
        "default": 100,
        "type": "int",
        "values": [],
        "tooltip": "# of iter to linearly decay learning rate to zero",
        "changeable": false
    },
    {
        "name": "beta1",
        "default": 0.9,
        "type": "float",
        "values": [],
        "tooltip": "momentum term of adam",
        "changeable": false
    },
    {
        "name": "lr",
        "default": 0.0001,
        "type": "float",
        "values": [],
        "tooltip": "initial learning rate for adam",
        "changeable": false
    },
    {
        "name": "no_lsgan",
        "default": true,
        "type": "bool",
        "values": [true, false],
        "tooltip": "do *not* use least square GAN, if false, use vanilla GAN",
        "changeable": false
    },
    {
        "name": "lambda_GAN",
        "default": 0.0,
        "type": "float",
        "values": [],
        "tooltip": "weight for GAN loss",
        "changeable": false
    },
    {
        "name": "lambda_A",
        "default": 1.0,
        "type": "float",
        "values": [],
        "tooltip": "weight for cycle loss (A -> B -> A)",
        "changeable": false
    },
    {
        "name": "lambda_B",
        "default": 1.0,
        "type": "float",
        "values": [],
        "tooltip": "weight for cycle loss (B -> A -> B)",
        "changeable": false
    },
    {
        "name": "lambda_identity",
        "default": 0.5,
        "type": "float",
        "values": [],
        "tooltip": "use identity mapping. Setting lambda_identity other than 0 has an effect of scaling the weight of the identity mapping loss.",
        "changeable": false
    },
    {
        "name": "pool_size",
        "default": 50,
        "type": "int",
        "values": [],
        "tooltip": "the size of image buffer that stores previously generated images",
        "changeable": false
    },
    {
        "name": "no_html",
        "default": true,
        "type": "bool",
        "values": [true, false],
        "tooltip": "do not save intermediate training results to [opt.checkpoints_dir]/[opt.name]/web/",
        "changeable": false
    },
    {
        "name": "lr_policy",
        "default": "lambda",
        "type": "string",
        "values": ["lambda", "step", "plateau"],
        "tooltip": "learning rate policy: lambda|step|plateau",
        "changeable": false
    },
    {
        "name": "lr_decay_iters",
        "default": 50,
        "type": "int",
        "values": [],
        "tooltip": "multiply by a gamma every lr_decay_iters iterations",
        "changeable": false
    },
    {
        "name": "avg_loss_alpha",
        "default": 0.986,
        "type": "float",
        "values": [],
        "tooltip": "exponential averaging weight for displaying loss",
        "changeable": false
    },
    {
        "name": "isTrain",
        "default": false,
        "type": "bool",
        "values": [true, false],
        "tooltip": "Always test",
        "changeable": false
    }
]


